python_ssg/__init__.py
python_ssg/api_client.py
python_ssg/site_renderer.py
python_ssg/storage.py
python_ssg/watch.py
python_ssr/__init__.py
python_ssr/api_client.py
python_ssr/site_renderer.py
python_ssr/storage.py
python_ssr/watch.py
python_ssg-0.0.1.dist-info/LICENSE
python_ssg-0.0.1.dist-info/METADATA
python_ssg-0.0.1.dist-info/WHEEL
python_ssg-0.0.1.dist-info/entry_points.txt
python_ssg-0.0.1.dist-info/top_level.txt
python_ssg-0.0.1.dist-info/RECORD
