Metadata-Version: 2.1
Name: python-ssg
Version: 0.0.1
Summary: A Python SSG library for dynamically generating static websites
Home-page: https://github.com/kayon-ariel/python-ssg
Author: Kayon Ariel
Author-email: kayonariel@gmail.com
License: MIT
Project-URL: Homepage, https://github.com/kayon-ariel/python-ssg
Project-URL: Repository, https://github.com/kayon-ariel/python-ssg.git
Project-URL: Issues, https://github.com/kayon-ariel/python-ssg/issues
Keywords: python ssg,static site generation,dynamic static sites
Classifier: Programming Language :: Python :: 3
Classifier: License :: OSI Approved :: MIT License
Classifier: Operating System :: OS Independent
Requires-Python: >=3.6
License-File: LICENSE
Requires-Dist: jinja2
Requires-Dist: requests
